[
  {
    "line": "Bus 65: Blasewitz => Luga",
    "segments": [
      {
        "junction": 347,
        "pos": [
          13.805204223429003,
          51.0521576015907
        ]
      },
      [
        13.8055336,
        51.0521429
      ],
      [
        13.8056265,
        51.0521421
      ],
      [
        13.8056741,
        51.0521416
      ],
      [
        13.8058721,
        51.0521399
      ],
      [
        13.8060914,
        51.0521376
      ],
      [
        13.8060914,
        51.0521376
      ],
      [
        13.8064475,
        51.0521295
      ],
      [
        13.8064945,
        51.0521273
      ],
      [
        13.8066462,
        51.0521153
      ],
      [
        13.8067582,
        51.052098
      ],
      [
        13.8067582,
        51.052098
      ],
      [
        13.8068573,
        51.0520686
      ],
      [
        13.8069489,
        51.0520282
      ],
      [
        13.807003,
        51.0519927
      ],
      [
        13.8071213,
        51.0519151
      ],
      [
        13.8071213,
        51.0519151
      ],
      [
        13.8072204,
        51.0518514
      ],
      [
        13.8072204,
        51.0518514
      ],
      [
        13.8073346,
        51.0517644
      ],
      [
        13.8074374,
        51.0516687
      ],
      [
        13.8074374,
        51.0516687
      ],
      [
        13.8078852,
        51.0512416
      ],
      [
        13.8080448,
        51.051103
      ],
      [
        13.8081472,
        51.0510126
      ],
      [
        13.8082185,
        51.0509512
      ],
      [
        13.808285316897704,
        51.050889195181114
      ],
      {
        "junction": 358,
        "pos": [
          13.802427708337099,
          51.029752270025426
        ]
      },
      [
        13.8023266,
        51.0296454
      ],
      [
        13.8022555,
        51.0295668
      ],
      [
        13.8021421,
        51.0294608
      ],
      [
        13.8019571,
        51.0292906
      ],
      [
        13.8018833,
        51.0291574
      ],
      [
        13.8018833,
        51.0291574
      ],
      [
        13.801645,
        51.0288655
      ],
      [
        13.8012874,
        51.0284036
      ],
      [
        13.8012874,
        51.0284036
      ],
      [
        13.8009972,
        51.0280321
      ],
      [
        13.8009972,
        51.0280321
      ],
      [
        13.8009085,
        51.0279179
      ],
      [
        13.8008758,
        51.0278768
      ],
      [
        13.8008046,
        51.0277861
      ],
      [
        13.8006957,
        51.0276475
      ],
      [
        13.8005858,
        51.0275077
      ],
      [
        13.8005702,
        51.0274879
      ],
      [
        13.8005444,
        51.027455
      ],
      [
        13.8004801,
        51.0273731
      ],
      [
        13.8004801,
        51.0273731
      ],
      [
        13.8004502,
        51.0273352
      ],
      [
        13.8004302,
        51.0273071
      ],
      [
        13.800426418663465,
        51.02730226529115
      ]
    ]
  },
  {
    "line": "Bus 65: Heidenau => Blasewitz",
    "segments": [
      {
        "junction": 358,
        "pos": [
          13.802525722981597,
          51.02966074400528
        ]
      },
      [
        13.8024668,
        51.0295966
      ],
      [
        13.8023582,
        51.0294958
      ],
      [
        13.8022561,
        51.0294126
      ],
      [
        13.8020466,
        51.0292524
      ],
      [
        13.8018833,
        51.0291574
      ],
      [
        13.8018833,
        51.0291574
      ],
      [
        13.801645,
        51.0288655
      ],
      [
        13.8012874,
        51.0284036
      ],
      [
        13.8012874,
        51.0284036
      ],
      [
        13.8009972,
        51.0280321
      ],
      [
        13.8009972,
        51.0280321
      ],
      [
        13.8009085,
        51.0279179
      ],
      [
        13.8008758,
        51.0278768
      ],
      [
        13.8008046,
        51.0277861
      ],
      [
        13.8006957,
        51.0276475
      ],
      [
        13.8005858,
        51.0275077
      ],
      [
        13.8005702,
        51.0274879
      ],
      [
        13.8005444,
        51.027455
      ],
      [
        13.8004801,
        51.0273731
      ],
      [
        13.8004801,
        51.0273731
      ],
      [
        13.8004502,
        51.0273352
      ],
      [
        13.8004302,
        51.0273071
      ],
      [
        13.800426418663465,
        51.02730226529115
      ]
    ]
  },
  {
    "line": "Bus 65: Blasewitz => Heidenau",
    "segments": [
      {
        "junction": 347,
        "pos": [
          13.805204223429003,
          51.0521576015907
        ]
      },
      [
        13.8055336,
        51.0521429
      ],
      [
        13.8056265,
        51.0521421
      ],
      [
        13.8056741,
        51.0521416
      ],
      [
        13.8058721,
        51.0521399
      ],
      [
        13.8060914,
        51.0521376
      ],
      [
        13.8060914,
        51.0521376
      ],
      [
        13.8064475,
        51.0521295
      ],
      [
        13.8064945,
        51.0521273
      ],
      [
        13.8066462,
        51.0521153
      ],
      [
        13.8067582,
        51.052098
      ],
      [
        13.8067582,
        51.052098
      ],
      [
        13.8068573,
        51.0520686
      ],
      [
        13.8069489,
        51.0520282
      ],
      [
        13.807003,
        51.0519927
      ],
      [
        13.8071213,
        51.0519151
      ],
      [
        13.8071213,
        51.0519151
      ],
      [
        13.8072204,
        51.0518514
      ],
      [
        13.8072204,
        51.0518514
      ],
      [
        13.8073346,
        51.0517644
      ],
      [
        13.8074374,
        51.0516687
      ],
      [
        13.8074374,
        51.0516687
      ],
      [
        13.8078852,
        51.0512416
      ],
      [
        13.8080448,
        51.051103
      ],
      [
        13.8081472,
        51.0510126
      ],
      [
        13.8082185,
        51.0509512
      ],
      [
        13.808285316897704,
        51.050889195181114
      ],
      {
        "junction": 358,
        "pos": [
          13.802427708337099,
          51.029752270025426
        ]
      },
      [
        13.8023266,
        51.0296454
      ],
      [
        13.8022555,
        51.0295668
      ],
      [
        13.8021421,
        51.0294608
      ],
      [
        13.8019571,
        51.0292906
      ],
      [
        13.8018833,
        51.0291574
      ],
      [
        13.8018833,
        51.0291574
      ],
      [
        13.801645,
        51.0288655
      ],
      [
        13.8012874,
        51.0284036
      ],
      [
        13.8012874,
        51.0284036
      ],
      [
        13.8009972,
        51.0280321
      ],
      [
        13.8009972,
        51.0280321
      ],
      [
        13.8009085,
        51.0279179
      ],
      [
        13.8008758,
        51.0278768
      ],
      [
        13.8008046,
        51.0277861
      ],
      [
        13.8006957,
        51.0276475
      ],
      [
        13.8005858,
        51.0275077
      ],
      [
        13.8005702,
        51.0274879
      ],
      [
        13.8005444,
        51.027455
      ],
      [
        13.8004801,
        51.0273731
      ],
      [
        13.8004801,
        51.0273731
      ],
      [
        13.8004502,
        51.0273352
      ],
      [
        13.8004302,
        51.0273071
      ],
      [
        13.800426418663465,
        51.02730226529115
      ]
    ]
  },
  {
    "line": "Bus 65: Luga => Blasewitz",
    "segments": [
      [
        13.7973593,
        51.0241668
      ],
      [
        13.7973593,
        51.0241668
      ],
      {
        "junction": 358,
        "pos": [
          13.7973593,
          51.0241668
        ]
      },
      [
        13.79748,
        51.0242856
      ],
      [
        13.7975451,
        51.0243497
      ],
      [
        13.7975451,
        51.0243497
      ],
      [
        13.7977855,
        51.0245921
      ],
      [
        13.7977855,
        51.0245921
      ],
      [
        13.7978716,
        51.0246795
      ],
      [
        13.7978903,
        51.0246984
      ],
      [
        13.7979414,
        51.02475
      ],
      [
        13.7979414,
        51.02475
      ],
      [
        13.7981857,
        51.0249967
      ],
      [
        13.7981995,
        51.0250106
      ],
      [
        13.7984863,
        51.0253003
      ],
      [
        13.7984863,
        51.0253003
      ],
      [
        13.7986745,
        51.0254912
      ],
      [
        13.7986745,
        51.0254912
      ],
      [
        13.7987717,
        51.0255885
      ],
      [
        13.7987919,
        51.0256089
      ],
      [
        13.79905,
        51.0258696
      ],
      [
        13.7993308,
        51.0261532
      ],
      [
        13.7994075,
        51.0262307
      ],
      [
        13.7994075,
        51.0262307
      ],
      [
        13.7996461,
        51.0264717
      ],
      [
        13.7998353,
        51.0266726
      ],
      [
        13.799884,
        51.0267216
      ],
      [
        13.799884,
        51.0267216
      ],
      [
        13.7999422,
        51.0267807
      ],
      [
        13.7999422,
        51.0267807
      ],
      [
        13.8000742,
        51.0269174
      ],
      [
        13.8002467,
        51.027095
      ],
      [
        13.8002796,
        51.0271323
      ],
      [
        13.8003099,
        51.0271667
      ],
      [
        13.8004022,
        51.0272713
      ],
      [
        13.8004022,
        51.0272713
      ],
      [
        13.800426418663465,
        51.02730226529115
      ],
      {
        "junction": 387,
        "pos": [
          13.800426418663465,
          51.02730226529115
        ]
      },
      [
        13.8004302,
        51.0273071
      ],
      [
        13.8004502,
        51.0273352
      ],
      [
        13.8004801,
        51.0273731
      ],
      [
        13.8004801,
        51.0273731
      ],
      [
        13.8005444,
        51.027455
      ],
      [
        13.8005702,
        51.0274879
      ],
      [
        13.8005858,
        51.0275077
      ],
      [
        13.8006957,
        51.0276475
      ],
      [
        13.8008046,
        51.0277861
      ],
      [
        13.8008758,
        51.0278768
      ],
      [
        13.8009085,
        51.0279179
      ],
      [
        13.8009972,
        51.0280321
      ],
      [
        13.8009972,
        51.0280321
      ],
      [
        13.8012874,
        51.0284036
      ],
      [
        13.8012874,
        51.0284036
      ],
      [
        13.801645,
        51.0288655
      ],
      [
        13.8018833,
        51.0291574
      ],
      [
        13.8018833,
        51.0291574
      ],
      [
        13.8020466,
        51.0292524
      ],
      [
        13.8022561,
        51.0294126
      ],
      [
        13.8023582,
        51.0294958
      ],
      [
        13.8024668,
        51.0295966
      ],
      [
        13.802525722981597,
        51.02966074400528
      ],
      {
        "junction": 357,
        "pos": [
          13.802525722981597,
          51.02966074400528
        ]
      },
      [
        13.8025695,
        51.0297084
      ],
      [
        13.802598,
        51.02974
      ],
      [
        13.8027741,
        51.0299356
      ],
      [
        13.802849,
        51.0300182
      ],
      [
        13.8028737,
        51.0300438
      ],
      [
        13.8029129,
        51.0300845
      ],
      [
        13.8029129,
        51.0300845
      ],
      [
        13.803435,
        51.0306508
      ],
      [
        13.8034642,
        51.0307209
      ],
      [
        13.8035547,
        51.0309383
      ],
      [
        13.8035547,
        51.0309383
      ],
      [
        13.8036838,
        51.0310796
      ],
      [
        13.803691,
        51.0310873
      ],
      [
        13.8046206,
        51.0320855
      ],
      [
        13.8046206,
        51.0320855
      ],
      [
        13.8047537,
        51.0322284
      ],
      [
        13.8048967,
        51.0323734
      ],
      [
        13.8048967,
        51.0323734
      ],
      [
        13.8050205,
        51.0325002
      ],
      [
        13.8050205,
        51.0325002
      ],
      [
        13.8052551,
        51.0327317
      ],
      [
        13.805269874443416,
        51.03274618811699
      ],
      {
        "junction": 357,
        "pos": [
          13.805269874443416,
          51.03274618811699
        ]
      },
      [
        13.8052809,
        51.032757
      ],
      [
        13.8054216,
        51.0328918
      ],
      [
        13.8057003,
        51.0331695
      ],
      [
        13.806057,
        51.0335202
      ],
      [
        13.8060958,
        51.0335579
      ],
      [
        13.8064258,
        51.0338828
      ],
      [
        13.8067869,
        51.034237
      ],
      [
        13.8070351,
        51.0344804
      ],
      [
        13.8071547,
        51.0345977
      ],
      [
        13.8071547,
        51.0345977
      ],
      [
        13.8073093,
        51.0347493
      ],
      [
        13.8073986,
        51.0348366
      ],
      [
        13.8074802,
        51.0349247
      ],
      [
        13.8074802,
        51.0349247
      ],
      [
        13.8075197,
        51.03499
      ],
      [
        13.8075417,
        51.0350496
      ],
      [
        13.8075539,
        51.0351257
      ],
      [
        13.8075348,
        51.0352091
      ],
      [
        13.8074959,
        51.0353176
      ],
      [
        13.8074428,
        51.0354383
      ],
      [
        13.8074428,
        51.0354383
      ],
      [
        13.8074364,
        51.0354533
      ],
      [
        13.8073843,
        51.0355754
      ],
      [
        13.8073492,
        51.0356576
      ],
      [
        13.807296,
        51.0357804
      ],
      [
        13.807296,
        51.0357804
      ],
      [
        13.8072797,
        51.035817
      ],
      [
        13.8070938,
        51.0362015
      ],
      [
        13.8070381,
        51.0363054
      ],
      [
        13.8070381,
        51.0363054
      ],
      [
        13.8068667,
        51.0366924
      ],
      [
        13.8065493,
        51.0374272
      ],
      [
        13.8065493,
        51.0374272
      ],
      [
        13.8063342,
        51.0378879
      ],
      [
        13.8063342,
        51.0378879
      ],
      [
        13.8062183,
        51.0381806
      ],
      [
        13.8061578,
        51.038364
      ],
      [
        13.806152,
        51.0383814
      ],
      [
        13.8060816,
        51.0387217
      ],
      [
        13.8060816,
        51.0387217
      ],
      [
        13.8060533,
        51.038851
      ],
      [
        13.8060533,
        51.038851
      ],
      [
        13.8060388,
        51.0389175
      ],
      [
        13.8060069,
        51.0390562
      ],
      [
        13.8060069,
        51.0390562
      ],
      [
        13.805977,
        51.0391815
      ],
      [
        13.8059703,
        51.03921
      ],
      [
        13.8059336,
        51.0393639
      ],
      [
        13.805922669140022,
        51.03940959457859
      ],
      [
        13.803695,
        51.0511102
      ],
      [
        13.803695,
        51.0511102
      ],
      {
        "junction": 346,
        "pos": [
          13.803695,
          51.0511102
        ]
      },
      [
        13.8035655,
        51.0513
      ],
      [
        13.8034067,
        51.0515327
      ],
      [
        13.8031864,
        51.0518308
      ],
      [
        13.8029661,
        51.0521177
      ],
      [
        13.8029661,
        51.0521177
      ],
      [
        13.8031808,
        51.0523087
      ],
      [
        13.8031894,
        51.0523163
      ],
      [
        13.8031894,
        51.0523163
      ],
      [
        13.8034131,
        51.0522794
      ],
      [
        13.8035866,
        51.0522533
      ],
      [
        13.8035866,
        51.0522533
      ],
      [
        13.8037901,
        51.052231
      ],
      [
        13.8038661,
        51.0522236
      ],
      [
        13.8039544,
        51.0522184
      ],
      [
        13.8040376,
        51.0522153
      ],
      [
        13.8040376,
        51.0522153
      ],
      [
        13.8044897,
        51.0521934
      ],
      [
        13.8044897,
        51.0521934
      ],
      [
        13.8047801,
        51.0521786
      ],
      [
        13.8051012,
        51.0521622
      ]
    ]
  }
]